{
  "project_info": {
    "project_number": "815437697637",
    "project_id": "contasa-96ddd",
    "storage_bucket": "contasa-96ddd.appspot.com"
  },
  "client": [
    {
      "client_info": {
        "mobilesdk_app_id": "1:815437697637:android:12f8bc22a3b548874a6c8c",
        "android_client_info": {
          "package_name": "com.example.contesta_na_hora"
        }
      },
      "oauth_client": [
        {
          "client_id": "815437697637-pk1fvgboml3uvs5vmol9d94irabchiag.apps.googleusercontent.com",
          "client_type": 3
        }
      ],
      "api_key": [
        {
          "current_key": "AIzaSyAH2gGdHTVCmrSOFtwN_DlQRCLAb_jndlY"
        }
      ],
      "services": {
        "appinvite_service": {
          "other_platform_oauth_client": [
            {
              "client_id": "815437697637-pk1fvgboml3uvs5vmol9d94irabchiag.apps.googleusercontent.com",
              "client_type": 3
            }
          ]
        }
      }
    }
  ],
  "configuration_version": "1"
}